dist_exe
