Metadata-Version: 2.1
Name: dist-exe
Version: 0.0.4
Summary: Distributed execution utility.
Home-page: https://github.com/glentner/dist_exe
Author: Geoffrey Lentner
Author-email: <glentner@purdue.edu>
License: Apache License 2.0
Keywords: distributed asynchronous queue
Platform: UNKNOWN
Classifier: Development Status :: 4 - Beta
Classifier: Programming Language :: Python :: 3.7
Classifier: License :: OSI Approved :: Apache Software License
